flask_telebot.py
Flask_Telebot-1.0.0.dist-info/LICENSE
Flask_Telebot-1.0.0.dist-info/METADATA
Flask_Telebot-1.0.0.dist-info/WHEEL
Flask_Telebot-1.0.0.dist-info/top_level.txt
Flask_Telebot-1.0.0.dist-info/RECORD
