Metadata-Version: 2.1
Name: Flask-Telebot
Version: 1.0.0
Summary: Telebot on flask
Home-page: https://github.com/GatLab/Flask-Telebot.git
Author: Gatlab
Author-email: Gatlab <dev@gatlab.co>
License: Copyright 2022 Gatlab <dev@gatlab.co>        
Project-URL: Homepage, https://github.com/GatLab/Flask-Telebot
Project-URL: Bug Tracker, https://github.com/GatLab/Flask-Telebot/issues
Platform: any
Classifier: Programming Language :: Python :: 3
Classifier: License :: OSI Approved :: MIT License
Classifier: Operating System :: OS Independent
Requires-Python: >=3.8
License-File: LICENSE
Requires-Dist: Flask
Requires-Dist: pyngrok
Requires-Dist: pyTelegramBotAPI
